svg2fbf/__init__.py
svg2fbf/text_to_path.py
auto_install_deps.py
svg2fbf/main.py
svg_viewbox_repair/__init__.py
svg_viewbox_repair/main.py
svg2fbf-0.1.19.data/data/share/svg2fbf/node_scripts/calculate_bbox.js
svg2fbf-0.1.19.data/data/share/svg2fbf/node_scripts/render_fbf_animation.js
svg2fbf-0.1.19.data/data/share/svg2fbf/node_scripts/render_svg.js
svg2fbf-0.1.19.data/data/share/svg2fbf/node_scripts/test_onload.js
svg2fbf-0.1.19.data/data/share/svg2fbf/node_scripts/test_onload_dispatch.js
svg2fbf-0.1.19.data/data/share/svg2fbf/node_scripts/test_onload_errors.js
svg2fbf-0.1.19.data/data/share/svg2fbf/node_scripts/test_script_execution.js
svg2fbf-0.1.19.data/data/share/svg2fbf/node_scripts/test_splat_button.js
svg2fbf-0.1.19.data/data/share/svg2fbf/package.json
svg2fbf-0.1.19.dist-info/METADATA
svg2fbf-0.1.19.dist-info/WHEEL
svg2fbf-0.1.19.dist-info/entry_points.txt
svg2fbf-0.1.19.dist-info/licenses/LICENSE
svg2fbf-0.1.19.dist-info/RECORD
