Metadata-Version: 2.4
Name: svg2fbf
Version: 0.1.19
Summary: SVG Frame-by-Frame Animation Generator - Create optimized FBF SVG animations from SVG sequences
Project-URL: Homepage, https://github.com/Emasoft/svg2fbf
Project-URL: Documentation, https://github.com/Emasoft/svg2fbf#readme
Project-URL: Repository, https://github.com/Emasoft/svg2fbf.git
Project-URL: Issues, https://github.com/Emasoft/svg2fbf/issues
Project-URL: Changelog, https://github.com/Emasoft/svg2fbf/blob/main/CHANGELOG.md
Author-email: Emasoft <713559+Emasoft@users.noreply.github.com>
Maintainer-email: Emasoft <713559+Emasoft@users.noreply.github.com>
License: Apache-2.0
License-File: LICENSE
Keywords: animation,fbf,frame-by-frame,mesh-gradient,smil,svg,svg2fbf,vector-animation
Classifier: Development Status :: 3 - Alpha
Classifier: Environment :: Console
Classifier: Intended Audience :: Developers
Classifier: Intended Audience :: End Users/Desktop
Classifier: License :: OSI Approved :: Apache Software License
Classifier: Operating System :: OS Independent
Classifier: Programming Language :: Python :: 3
Classifier: Programming Language :: Python :: 3.11
Classifier: Programming Language :: Python :: 3.12
Classifier: Programming Language :: Python :: 3.13
Classifier: Topic :: Multimedia :: Graphics :: Editors :: Vector-Based
Classifier: Topic :: Multimedia :: Graphics :: Graphics Conversion
Classifier: Topic :: Software Development :: Libraries :: Python Modules
Classifier: Typing :: Typed
Requires-Python: >=3.11
Requires-Dist: fonttools>=4.60.1
Requires-Dist: lxml>=6.0.2
Requires-Dist: numpy>=2.2.0
Requires-Dist: python-bidi>=0.6.7
Requires-Dist: pyyaml>=6.0
Requires-Dist: tomli-w>=1.2.0
Provides-Extra: text2path
Requires-Dist: svg-text2path>=0.5.0; extra == 'text2path'
